{
  "_fv": 47,
  "_type": "villagertrade",
  "definition": {
    "tradeEntries": [
      {
        "villagerProfession": {
          "value": "ARMORER"
        },
        "entries": [
          {
            "price1": {
              "value": "Items.EMERALD"
            },
            "countPrice1": 5,
            "price2": {
              "value": ""
            },
            "countPrice2": 1,
            "offer": {
              "value": "CUSTOM:SilversArmor.body"
            },
            "countOffer": 1,
            "level": 1,
            "maxTrades": 10,
            "xp": 5,
            "priceMultiplier": 0.05
          }
        ]
      },
      {
        "villagerProfession": {
          "value": "WEAPONSMITH"
        },
        "entries": [
          {
            "price1": {
              "value": "Items.EMERALD"
            },
            "countPrice1": 3,
            "price2": {
              "value": ""
            },
            "countPrice2": 1,
            "offer": {
              "value": "CUSTOM:SilversSword"
            },
            "countOffer": 1,
            "level": 1,
            "maxTrades": 10,
            "xp": 5,
            "priceMultiplier": 0.05
          }
        ]
      },
      {
        "villagerProfession": {
          "value": "TOOLSMITH"
        },
        "entries": [
          {
            "price1": {
              "value": "Items.EMERALD"
            },
            "countPrice1": 6,
            "price2": {
              "value": ""
            },
            "countPrice2": 1,
            "offer": {
              "value": "CUSTOM:SilversPickaxe"
            },
            "countOffer": 1,
            "level": 1,
            "maxTrades": 10,
            "xp": 5,
            "priceMultiplier": 0.05
          }
        ]
      }
    ]
  }
}